nonebot_plugin_acc_calculate/__init__.py
nonebot_plugin_acc_calculate/data_source.py
nonebot_plugin_acc_calculate/database.py
nonebot_plugin_acc_calculate-1.0.0.dist-info/LICENSE
nonebot_plugin_acc_calculate-1.0.0.dist-info/METADATA
nonebot_plugin_acc_calculate-1.0.0.dist-info/WHEEL
nonebot_plugin_acc_calculate-1.0.0.dist-info/top_level.txt
nonebot_plugin_acc_calculate-1.0.0.dist-info/RECORD
