Metadata-Version: 2.1
Name: nonebot-plugin-acc-calculate
Version: 1.0.0
Summary: Nonebot2 段位单曲acc计算
Home-page: https://github.com/ohdmire/nonebot-plugin-acc-calculate
Author: ohdmire
Author-email: 1750011571@qq.com
Project-URL: Bug Tracker, https://github.com/ohdmire/nonebot-plugin-acc-calculate/issues
Requires-Python: >=3.8,<4.0
License-File: LICENSE
